{
  "name": "Redwood Viz",
  "description": "Example Viz",
  "layout": {
    "type": "grid",
    "details": [
      {
        "cols": 2,
        "rows": 2
      }
    ]
  },
  "data": [
    {
      "name": "table",
      "values": [
        {
          "name": "Page A", "uv": 4000, "pv": 2400, "amt": 2400
        },
        {
          "name": "Page B", "uv": 3000, "pv": 1398, "amt": 2210
        },
        {
          "name": "Page C", "uv": 2000, "pv": 9800, "amt": 2290
        },
        {
          "name": "Page D", "uv": 2780, "pv": 3908, "amt": 2000
        },
        {
          "name": "Page E", "uv": 1890, "pv": 4800, "amt": 2181
        },
        {
          "name": "Page F", "uv": 2390, "pv": 3800, "amt": 2500
        },
        {
          "name": "Page G", "uv": 3490, "pv": 4300, "amt": 2100
        }
      ]
    },
    {
      "name": "scatter-table",
      "values": [{"id":"group A","data":[{"x":80,"y":74},{"x":27,"y":25},{"x":22,"y":18},{"x":0,"y":86},{"x":5,"y":46},{"x":63,"y":43},{"x":65,"y":27},{"x":47,"y":101},{"x":13,"y":92},{"x":86,"y":112},{"x":93,"y":72},{"x":82,"y":78},{"x":9,"y":79},{"x":60,"y":4},{"x":8,"y":54},{"x":72,"y":34},{"x":43,"y":97},{"x":6,"y":8},{"x":21,"y":100},{"x":0,"y":69},{"x":43,"y":40},{"x":33,"y":111},{"x":20,"y":53},{"x":34,"y":112},{"x":19,"y":15},{"x":7,"y":16},{"x":77,"y":118},{"x":78,"y":60},{"x":90,"y":95},{"x":65,"y":49},{"x":90,"y":31},{"x":33,"y":12},{"x":40,"y":115},{"x":27,"y":5},{"x":65,"y":77},{"x":25,"y":10},{"x":68,"y":25},{"x":19,"y":72},{"x":18,"y":120},{"x":22,"y":35},{"x":92,"y":2},{"x":45,"y":53},{"x":46,"y":66},{"x":0,"y":67},{"x":20,"y":10},{"x":16,"y":117},{"x":54,"y":79},{"x":36,"y":76},{"x":58,"y":13},{"x":63,"y":12}]},{"id":"group B","data":[{"x":89,"y":73},{"x":1,"y":114},{"x":75,"y":104},{"x":87,"y":106},{"x":85,"y":92},{"x":84,"y":12},{"x":65,"y":6},{"x":51,"y":50},{"x":65,"y":115},{"x":68,"y":44},{"x":85,"y":28},{"x":28,"y":34},{"x":40,"y":58},{"x":75,"y":74},{"x":61,"y":109},{"x":34,"y":54},{"x":91,"y":47},{"x":40,"y":100},{"x":90,"y":69},{"x":87,"y":54},{"x":76,"y":56},{"x":98,"y":86},{"x":100,"y":28},{"x":15,"y":59},{"x":2,"y":44},{"x":23,"y":40},{"x":16,"y":33},{"x":89,"y":96},{"x":47,"y":27},{"x":32,"y":43},{"x":10,"y":27},{"x":17,"y":105},{"x":63,"y":22},{"x":98,"y":85},{"x":58,"y":84},{"x":75,"y":42},{"x":78,"y":10},{"x":58,"y":39},{"x":94,"y":33},{"x":72,"y":51},{"x":16,"y":80},{"x":93,"y":22},{"x":97,"y":98},{"x":48,"y":49},{"x":68,"y":21},{"x":21,"y":10},{"x":11,"y":70},{"x":3,"y":90},{"x":56,"y":81},{"x":10,"y":79}]},{"id":"group C","data":[{"x":73,"y":85},{"x":16,"y":7},{"x":40,"y":38},{"x":49,"y":18},{"x":83,"y":27},{"x":86,"y":34},{"x":77,"y":51},{"x":12,"y":112},{"x":72,"y":94},{"x":83,"y":72},{"x":97,"y":41},{"x":24,"y":21},{"x":72,"y":62},{"x":43,"y":36},{"x":27,"y":24},{"x":82,"y":91},{"x":53,"y":38},{"x":72,"y":19},{"x":92,"y":68},{"x":31,"y":77},{"x":81,"y":113},{"x":40,"y":42},{"x":62,"y":43},{"x":24,"y":73},{"x":10,"y":89},{"x":66,"y":92},{"x":5,"y":31},{"x":71,"y":37},{"x":10,"y":51},{"x":19,"y":32},{"x":51,"y":86},{"x":23,"y":2},{"x":98,"y":34},{"x":11,"y":106},{"x":60,"y":101},{"x":57,"y":93},{"x":8,"y":18},{"x":74,"y":4},{"x":81,"y":29},{"x":72,"y":17},{"x":58,"y":77},{"x":69,"y":64},{"x":93,"y":113},{"x":55,"y":103},{"x":51,"y":65},{"x":5,"y":28},{"x":13,"y":46},{"x":91,"y":94},{"x":56,"y":27},{"x":41,"y":26}]},{"id":"group D","data":[{"x":84,"y":4},{"x":20,"y":53},{"x":95,"y":67},{"x":96,"y":31},{"x":75,"y":94},{"x":2,"y":33},{"x":70,"y":72},{"x":66,"y":71},{"x":44,"y":69},{"x":96,"y":82},{"x":91,"y":111},{"x":29,"y":14},{"x":84,"y":77},{"x":47,"y":17},{"x":22,"y":63},{"x":45,"y":107},{"x":53,"y":101},{"x":20,"y":65},{"x":54,"y":116},{"x":67,"y":91},{"x":1,"y":116},{"x":13,"y":2},{"x":68,"y":19},{"x":60,"y":104},{"x":63,"y":0},{"x":74,"y":96},{"x":45,"y":31},{"x":21,"y":111},{"x":28,"y":5},{"x":19,"y":34},{"x":82,"y":79},{"x":66,"y":54},{"x":29,"y":0},{"x":40,"y":102},{"x":47,"y":8},{"x":94,"y":85},{"x":45,"y":107},{"x":8,"y":47},{"x":95,"y":90},{"x":47,"y":3},{"x":9,"y":72},{"x":5,"y":6},{"x":47,"y":48},{"x":4,"y":90},{"x":42,"y":97},{"x":90,"y":1},{"x":84,"y":84},{"x":58,"y":70},{"x":38,"y":88},{"x":56,"y":29}]},{"id":"group E","data":[{"x":86,"y":19},{"x":25,"y":113},{"x":50,"y":81},{"x":50,"y":97},{"x":61,"y":77},{"x":40,"y":28},{"x":93,"y":77},{"x":41,"y":71},{"x":95,"y":103},{"x":79,"y":86},{"x":47,"y":49},{"x":26,"y":25},{"x":86,"y":28},{"x":70,"y":51},{"x":78,"y":95},{"x":51,"y":29},{"x":23,"y":33},{"x":16,"y":71},{"x":41,"y":110},{"x":86,"y":40},{"x":8,"y":0},{"x":29,"y":14},{"x":15,"y":65},{"x":92,"y":80},{"x":50,"y":81},{"x":96,"y":68},{"x":72,"y":109},{"x":81,"y":60},{"x":95,"y":116},{"x":40,"y":71},{"x":65,"y":13},{"x":47,"y":44},{"x":83,"y":29},{"x":29,"y":92},{"x":37,"y":90},{"x":56,"y":47},{"x":70,"y":87},{"x":54,"y":78},{"x":34,"y":16},{"x":42,"y":72},{"x":54,"y":94},{"x":53,"y":120},{"x":90,"y":38},{"x":10,"y":114},{"x":7,"y":87},{"x":81,"y":102},{"x":61,"y":77},{"x":84,"y":92},{"x":49,"y":59},{"x":71,"y":0}]}]
    }
  ],
  "charts": [
    { "type": "line", "data": "table", "height": 300,
      "axes": {
        "x": {
          "label": "name",
          "dataColumn": "name"
        },
        "y": {
          "label": "count",
          "dataColumns": [
            {"name": "uv", "color": "#8884d8"},
            {"name": "pv", "color": "#82ca9d"}
          ]
        }
      }
    },
    { "type": "bar", "data": "table", "height": 300,
      "axes": {
        "x": {
          "label": "name",
          "dataColumn": "name"
        },
        "y": {
          "label": "count",
          "dataColumns": [
            {"name": "uv", "color": "#8884d8"},
            {"name": "pv", "color": "#82ca9d"}
          ]
        }
      }
    },
    { "type": "scatter", "data": "scatter-table", "height": 300,
      "axes": {
        "x": {
          "label": "weight",
          "dataColumn": "name"
        },
        "y": {
          "label": "size",
          "dataColumns": [
            {"name": "uv", "color": "#8884d8"},
            {"name": "pv", "color": "#82ca9d"}
          ]
        }
      }
    },
    { "type": "area", "data": "table", "height": 300,
      "axes": {
        "x": {
          "label": "name",
          "dataColumn": "name"
        },
        "y": {
          "label": "count",
          "dataColumns": [
            {"name": "uv", "color": "#8884d8"},
            {"name": "pv", "color": "#82ca9d"}
          ]
        }
      }
    }
  ]
}